mirage/__init__.py
mirage/search.py
mirage_d1sak0-0.1.0.dist-info/licenses/LICENCE
mirage_d1sak0-0.1.0.dist-info/METADATA
mirage_d1sak0-0.1.0.dist-info/WHEEL
mirage_d1sak0-0.1.0.dist-info/top_level.txt
mirage_d1sak0-0.1.0.dist-info/RECORD
